{
    "145": {
        "status": "won",
        "groups": [
            {
                "number": 3,
                "theme": "Advérbios de lugar",
                "words": ["lá", "ali", "aqui", "acolá"]
            },
            {
                "number": 2,
                "theme": "Fontes de energia",
                "words": ["vento", "sol", "carvão", "água"]
            },
            {
                "number": 4,
                "theme": "Participantes num processo judicial",
                "words": ["ré", "juíza", "testemunha", "autora"]
            },
            {
                "number": 1,
                "theme": "Notas musicais",
                "words": ["dó", "mi", "si", "fá"]
            }
        ],
        "items": [],
        "selected": [],
        "attempts": [
            { "selected": ["mi", "lá", "si", "sol"] },
            { "selected": ["mi", "lá", "si", "fá"] },
            { "selected": ["fá", "mi", "lá", "si"] },
            { "selected": ["dó", "ré", "mi", "fá"] },
            { "selected": ["ré", "lá", "fá", "dó"] },
            { "selected": ["aqui", "lá", "acolá", "ali"], "group": 3 },
            { "selected": ["dó", "mi", "si", "ré"] },
            { "selected": ["testemunha", "juíza", "autora", "água"] },
            { "selected": ["água", "carvão", "vento", "sol"], "group": 2 },
            { "selected": ["autora", "testemunha", "fá", "juíza"] },
            { "selected": ["fá", "dó", "ré", "mi"] },
            { "selected": ["fá", "dó", "ré", "juíza"] },
            { "selected": ["fá", "dó", "ré", "juíza"] },
            { "selected": ["autora", "testemunha", "juíza", "si"] },
            { "selected": ["autora", "testemunha", "dó", "juíza"] },
            { "selected": ["dó", "testemunha", "ré", "juíza"] },
            { "selected": ["testemunha", "juíza", "ré", "autora"], "group": 4 },
            { "selected": ["dó", "mi", "fá", "si"], "group": 1 }
        ]
    },
    "147": {
        "status": "selecting",
        "groups": [],
        "items": [
            "sol",
            "brincadeira",
            "costas",
            "bono",
            "inquieto",
            "negresco",
            "distração",
            "levado",
            "passatempo",
            "arteiro",
            "traquinas",
            "chuva",
            "lazer",
            "aymoré",
            "roupa",
            "entretenimento"
        ],
        "selected": [],
        "attempts": [{ "selected": ["sol", "brincadeira", "costas", "bono"] }]
    },
    "160": {
        "status": "selecting",
        "groups": [],
        "items": [
            "processador",
            "cooler",
            "vida",
            "forca",
            "rede",
            "souvenir",
            "usb",
            "lightning",
            "bicho",
            "hdmi",
            "lembrança",
            "velha",
            "memória",
            "ssd",
            "mimo",
            "placa de vídeo"
        ],
        "selected": [],
        "attempts": []
    },
    "202": {
        "status": "won",
        "groups": [
            {
                "number": 1,
                "theme": "Tem no circo",
                "words": ["lona", "picadeiro", "equilibrista", "mágico"]
            },
            {
                "number": 2,
                "theme": "Quadriláteros",
                "words": ["retângulo", "quadrado", "trapézio", "paralelogramo"]
            },
            {
                "number": 3,
                "theme": "Tipos de torresmo",
                "words": ["rolo", "tira", "pururuca", "barriga"]
            },
            {
                "number": 4,
                "theme": "Símbolos dos naipes de baralho",
                "words": ["coração", "losango", "trevo", "ponta de lança"]
            }
        ],
        "items": [],
        "selected": [],
        "attempts": [
            { "selected": ["retângulo", "trapézio", "quadrado", "losango"] },
            {
                "selected": ["paralelogramo", "losango", "trapézio", "quadrado"]
            },
            {
                "selected": [
                    "retângulo",
                    "trapézio",
                    "losango",
                    "paralelogramo"
                ]
            },
            {
                "selected": [
                    "losango",
                    "paralelogramo",
                    "quadrado",
                    "retângulo"
                ]
            },
            { "hints": ["lona", "picadeiro"] },
            {
                "selected": ["picadeiro", "lona", "mágico", "equilibrista"],
                "group": 1
            },
            {
                "selected": [
                    "losango",
                    "paralelogramo",
                    "retângulo",
                    "trapézio"
                ]
            },
            {
                "selected": ["quadrado", "losango", "paralelogramo", "trapézio"]
            },
            { "selected": ["pururuca", "tira", "ponta de lança", "coração"] },
            { "selected": ["barriga", "coração", "ponta de lança", "rolo"] },
            { "selected": ["trevo", "pururuca", "ponta de lança", "tira"] },
            {
                "selected": [
                    "losango",
                    "paralelogramo",
                    "ponta de lança",
                    "retângulo"
                ]
            },
            {
                "selected": ["losango", "paralelogramo", "quadrado", "trapézio"]
            },
            {
                "selected": [
                    "retângulo",
                    "trapézio",
                    "paralelogramo",
                    "losango"
                ]
            },
            {
                "selected": [
                    "retângulo",
                    "quadrado",
                    "losango",
                    "paralelogramo"
                ]
            },
            {
                "selected": ["trapézio", "paralelogramo", "losango", "quadrado"]
            },
            {
                "selected": [
                    "paralelogramo",
                    "quadrado",
                    "retângulo",
                    "trapézio"
                ],
                "group": 2
            },
            { "selected": ["losango", "trevo", "pururuca", "barriga"] },
            { "selected": ["rolo", "losango", "trevo", "tira"] },
            { "selected": ["coração", "barriga", "rolo", "pururuca"] },
            { "selected": ["losango", "trevo", "tira", "barriga"] },
            { "selected": ["losango", "trevo", "barriga", "ponta de lança"] },
            { "selected": ["losango", "tira", "coração", "rolo"] },
            { "selected": ["losango", "coração", "rolo", "pururuca"] },
            { "selected": ["barriga", "ponta de lança", "pururuca", "trevo"] },
            { "selected": ["ponta de lança", "tira", "coração", "rolo"] },
            { "selected": ["tira", "losango", "rolo", "ponta de lança"] },
            { "selected": ["losango", "trevo", "rolo", "ponta de lança"] },
            { "selected": ["ponta de lança", "losango", "pururuca", "rolo"] },
            { "selected": ["tira", "trevo", "ponta de lança", "pururuca"] },
            { "selected": ["tira", "trevo", "losango", "rolo"] },
            { "selected": ["tira", "trevo", "losango", "coração"] },
            {
                "selected": ["losango", "coração", "ponta de lança", "pururuca"]
            },
            { "selected": ["barriga", "trevo", "rolo", "coração"] },
            { "selected": ["tira", "ponta de lança", "pururuca", "rolo"] },
            { "selected": ["coração", "losango", "rolo", "pururuca"] },
            { "selected": ["ponta de lança", "coração", "rolo", "barriga"] },
            { "selected": ["tira", "ponta de lança", "trevo", "pururuca"] },
            { "selected": ["losango", "coração", "rolo", "barriga"] },
            { "selected": ["losango", "tira", "pururuca", "ponta de lança"] },
            { "selected": ["losango", "coração", "ponta de lança", "rolo"] },
            { "selected": ["trevo", "barriga", "tira", "pururuca"] },
            { "selected": ["losango", "tira", "rolo", "trevo"] },
            { "selected": ["coração", "pururuca", "barriga", "trevo"] },
            { "selected": ["barriga", "trevo", "coração", "losango"] },
            { "selected": ["ponta de lança", "coração", "trevo", "tira"] },
            { "selected": ["rolo", "tira", "trevo", "pururuca"] },
            { "selected": ["tira", "losango", "rolo", "pururuca"] },
            { "selected": ["tira", "trevo", "rolo", "losango"] },
            { "selected": ["coração", "ponta de lança", "pururuca", "rolo"] },
            { "selected": ["trevo", "tira", "rolo", "pururuca"] },
            { "selected": ["barriga", "coração", "ponta de lança", "rolo"] },
            { "selected": ["barriga", "tira", "losango", "trevo"] },
            { "hints": ["rolo", "tira"] },
            { "selected": ["rolo", "tira", "ponta de lança", "trevo"] },
            { "selected": ["tira", "rolo", "pururuca", "coração"] },
            { "selected": ["rolo", "tira", "trevo", "ponta de lança"] },
            { "selected": ["tira", "rolo", "losango", "barriga"] },
            { "hints": ["rolo", "tira", "pururuca"] },
            { "selected": ["pururuca", "rolo", "tira", "trevo"] },
            { "selected": ["rolo", "pururuca", "tira", "ponta de lança"] },
            { "selected": ["tira", "losango", "rolo", "pururuca"] },
            { "selected": ["tira", "trevo", "rolo", "pururuca"] },
            { "selected": ["pururuca", "rolo", "barriga", "tira"], "group": 3 },
            {
                "selected": ["coração", "ponta de lança", "trevo", "losango"],
                "group": 4
            }
        ],
        "hints": []
    },
    "null": {
        "status": "selecting",
        "groups": [],
        "items": [],
        "selected": [],
        "attempts": []
    }
}
